ihook/__init__.py
ihook-0.2.1.dist-info/licenses/LICENSE
ihook-0.2.1.dist-info/METADATA
ihook-0.2.1.dist-info/WHEEL
ihook-0.2.1.dist-info/top_level.txt
ihook-0.2.1.dist-info/RECORD
